muninn_ecmwfmars.py
muninn_ecmwfmars-1.3.dist-info/LICENSE
muninn_ecmwfmars-1.3.dist-info/METADATA
muninn_ecmwfmars-1.3.dist-info/WHEEL
muninn_ecmwfmars-1.3.dist-info/top_level.txt
muninn_ecmwfmars-1.3.dist-info/RECORD
