Metadata-Version: 2.1
Name: muninn-ecmwfmars
Version: 1.3
Summary: Muninn extension for ECMWF GRIB products from the mars archive
Home-page: https://github.com/stcorp/muninn-ecmwfmars
Author: S[&]T
Author-email: UNKNOWN
License: BSD
Platform: UNKNOWN
Classifier: Development Status :: 5 - Production/Stable
Classifier: Programming Language :: Python :: 2
Classifier: Programming Language :: Python :: 3
Classifier: License :: OSI Approved :: BSD License
Classifier: Operating System :: OS Independent
Classifier: Topic :: Scientific/Engineering
Classifier: Environment :: Plugins
Requires-Dist: muninn
